blaulichtsms/__init__.py
blaulichtsms/__version__.py
blaulichtsms_api-0.1.1.dist-info/METADATA
blaulichtsms_api-0.1.1.dist-info/WHEEL
blaulichtsms_api-0.1.1.dist-info/licenses/LICENSE
blaulichtsms_api-0.1.1.dist-info/RECORD
