Metadata-Version: 2.1
Name: blaulichtsms-api
Version: 0.1.1
Summary: Client for BlaulichtSMS API
Project-URL: Homepage, https://gitlab.com/matthias_gilch/blaulichtsms-dashboard
Project-URL: Repository, https://gitlab.com/matthias_gilch/blaulichtsms-dashboard.git
Project-URL: Issues, https://gitlab.com/matthias_gilch/blaulichtsms-dashboard/-/issues
Author-email: Matthias Gilch <matthias.gilch.mg@gmail.com>
Maintainer-email: Matthias Gilch <matthias.gilch.mg@gmail.com>
License-File: LICENSE
Classifier: Development Status :: 3 - Alpha
Classifier: Intended Audience :: Developers
Classifier: License :: OSI Approved :: MIT License
Classifier: Programming Language :: Python
Classifier: Programming Language :: Python :: 3
Classifier: Programming Language :: Python :: 3.8
Classifier: Programming Language :: Python :: 3.9
Classifier: Programming Language :: Python :: 3.10
Classifier: Programming Language :: Python :: 3.11
Requires-Python: >=3.9
Requires-Dist: requests>=2.31.0
